tmplmatching/README.MD
tmplmatching/__init__.py
tmplmatching/canvas.min.js
tmplmatching/filesaver.min.js
tmplmatching/jszip.min.js
tmplmatching/requirements.txt
tmplmatching/thirdparty.json
tmplmatching/ybat.css
tmplmatching/ybat.html
tmplmatching/ybat.js
tmplmatching-0.12.dist-info/LICENSE.rst
tmplmatching-0.12.dist-info/METADATA
tmplmatching-0.12.dist-info/WHEEL
tmplmatching-0.12.dist-info/top_level.txt
tmplmatching-0.12.dist-info/RECORD
