Metadata-Version: 2.1
Name: tmplmatching
Version: 0.12
Summary: Fast multitemplate matching with support for different sizes using numexpr / cupy / fftw / scipy / multiprocessing
Home-page: https://github.com/hansalemaos/tmplmatching
Author: Johannes Fischer
Author-email: aulasparticularesdealemaosp@gmail.com
License: MIT
Keywords: template,matching
Classifier: Development Status :: 4 - Beta
Classifier: Programming Language :: Python :: 3 :: Only
Classifier: Programming Language :: Python :: 3.10
Classifier: Topic :: Software Development :: Libraries :: Python Modules
Classifier: Topic :: Utilities
License-File: LICENSE.rst
Requires-Dist: a-cv2-easy-resize
Requires-Dist: a-cv-imwrite-imread-plus
Requires-Dist: downloadunzip
Requires-Dist: intersectioncalc
Requires-Dist: list-all-files-recursively
Requires-Dist: mss
Requires-Dist: numexpr
Requires-Dist: numpy
Requires-Dist: numpydoc
Requires-Dist: opencv-python
Requires-Dist: pandas
Requires-Dist: pyFFTW
Requires-Dist: scipy
Requires-Dist: tolerant-isinstance
Requires-Dist: touchtouch
